MANIFEST.in
README.txt
setup.py
docs/HISTORY.txt
docs/LICENSE.txt
src/infrae/__init__.py
src/infrae.testing.egg-info/PKG-INFO
src/infrae.testing.egg-info/SOURCES.txt
src/infrae.testing.egg-info/dependency_links.txt
src/infrae.testing.egg-info/entry_points.txt
src/infrae.testing.egg-info/namespace_packages.txt
src/infrae.testing.egg-info/not-zip-safe
src/infrae.testing.egg-info/requires.txt
src/infrae.testing.egg-info/top_level.txt
src/infrae/testing/__init__.py
src/infrae/testing/events.py
src/infrae/testing/layers.py
src/infrae/testing/testcase.py
src/infrae/testing/testmethods.py
src/infrae/testing/xmlindent.py
src/infrae/testing/zope2.py